COPYING
README
setup.py
pyrocumulus/__init__.py
pyrocumulus/auth.py
pyrocumulus/conf.py
pyrocumulus/converters.py
pyrocumulus/db.py
pyrocumulus/exceptions.py
pyrocumulus/parsers.py
pyrocumulus/testing.py
pyrocumulus/utils.py
pyrocumulus.egg-info/PKG-INFO
pyrocumulus.egg-info/SOURCES.txt
pyrocumulus.egg-info/dependency_links.txt
pyrocumulus.egg-info/requires.txt
pyrocumulus.egg-info/top_level.txt
pyrocumulus/commands/__init__.py
pyrocumulus/commands/authcli.py
pyrocumulus/commands/base.py
pyrocumulus/commands/createproject.py
pyrocumulus/commands/runtornado.py
pyrocumulus/commands/test.py
pyrocumulus/web/__init__.py
pyrocumulus/web/applications.py
pyrocumulus/web/decorators.py
pyrocumulus/web/handlers.py
pyrocumulus/web/metaclasses.py
pyrocumulus/web/mixins.py
pyrocumulus/web/operationmappers.py
pyrocumulus/web/request_handlers.py
pyrocumulus/web/template.py
pyrocumulus/web/urlmappers.py
script/pyrocumulus